bio_image_unet/.DS_Store
bio_image_unet/__init__.py
bio_image_unet/multi_output_unet/__init__.py
bio_image_unet/multi_output_unet/data.py
bio_image_unet/multi_output_unet/losses.py
bio_image_unet/multi_output_unet/multi_output_nested_unet.py
bio_image_unet/multi_output_unet/multi_output_unet.py
bio_image_unet/multi_output_unet/predict.py
bio_image_unet/multi_output_unet/train.py
bio_image_unet/multi_output_unet3d/__init__.py
bio_image_unet/multi_output_unet3d/data.py
bio_image_unet/multi_output_unet3d/losses.py
bio_image_unet/multi_output_unet3d/multi_output_unet3d.py
bio_image_unet/multi_output_unet3d/predict.py
bio_image_unet/multi_output_unet3d/train.py
bio_image_unet/progress/__init__.py
bio_image_unet/progress/note.txt
bio_image_unet/progress/progressnotifier.py
bio_image_unet/siam_unet/.DS_Store
bio_image_unet/siam_unet/__init__.py
bio_image_unet/siam_unet/data.py
bio_image_unet/siam_unet/helpers/__cpu_count__.py
bio_image_unet/siam_unet/helpers/__md5sum__.py
bio_image_unet/siam_unet/helpers/average_tifs.py
bio_image_unet/siam_unet/helpers/create_pixel_value_histogram.py
bio_image_unet/siam_unet/helpers/cuda_test.py
bio_image_unet/siam_unet/helpers/extract_frame_of_movie.py
bio_image_unet/siam_unet/helpers/find_frame_of_image.py
bio_image_unet/siam_unet/helpers/generate_plain_image.py
bio_image_unet/siam_unet/helpers/generate_siam_unet_input_imgs.py
bio_image_unet/siam_unet/helpers/low_mem_tif_utils.py
bio_image_unet/siam_unet/helpers/threshold_images.py
bio_image_unet/siam_unet/helpers/tif_to_mp4.py
bio_image_unet/siam_unet/helpers/util.py
bio_image_unet/siam_unet/losses.py
bio_image_unet/siam_unet/predict.py
bio_image_unet/siam_unet/siam_unet.py
bio_image_unet/siam_unet/train.py
bio_image_unet/unet/__init__.py
bio_image_unet/unet/attention_unet.py
bio_image_unet/unet/baby_unet.py
bio_image_unet/unet/data.py
bio_image_unet/unet/losses.py
bio_image_unet/unet/predict.py
bio_image_unet/unet/train.py
bio_image_unet/unet/unet.py
bio_image_unet/unet/unet_v0.py
bio_image_unet-1.1.2.dist-info/LICENSE
bio_image_unet-1.1.2.dist-info/METADATA
bio_image_unet-1.1.2.dist-info/WHEEL
bio_image_unet-1.1.2.dist-info/RECORD
