Metadata-Version: 2.3
Name: bio-image-unet
Version: 1.1.2
Summary: Implementations of U-Net, Siam U-Net, U-Net++ and 3D U-Net for biological image segmentation
Home-page: https://github.com/danihae/bio-image-unet
License: MIT
Author: Daniel Haertter
Requires-Python: >=3.8,<4.0
Classifier: License :: OSI Approved :: MIT License
Classifier: Programming Language :: Python :: 3
Classifier: Programming Language :: Python :: 3.8
Classifier: Programming Language :: Python :: 3.9
Classifier: Programming Language :: Python :: 3.10
Classifier: Programming Language :: Python :: 3.11
Classifier: Programming Language :: Python :: 3.12
Classifier: Programming Language :: Python :: 3.13
Requires-Dist: albumentations (>=1.4.24,<2.0.0)
Requires-Dist: matplotlib (==3.*)
Requires-Dist: napari (>0.4.18)
Requires-Dist: numpy (>1.20)
Requires-Dist: packaging
Requires-Dist: scikit-image (>0.18,<1.0)
Requires-Dist: tensorboard
Requires-Dist: tifffile
Requires-Dist: torch (==2.*)
Requires-Dist: tqdm
Project-URL: Repository, https://github.com/danihae/bio-image-unet
